{"starter":{"image":"https://raw.githubusercontent.com/PokeAPI/sprites/master/sprites/pokemon/7.png","name":"squirtle"},"caught":[{"name":"golem","qt":1},{"name":"anorith","qt":1},{"name":"slowbro","qt":1},{"name":"genesect","qt":1},{"name":"electrike","qt":1},{"name":"raticate","qt":1},{"name":"piloswine","qt":1},{"name":"entei","qt":1},{"name":"arcanine","qt":1},{"name":"musharna","qt":1},{"name":"qwilfish","qt":1},{"name":"wynaut","qt":1},{"name":"gourgeist-average","qt":1},{"name":"vaporeon","qt":1},{"name":"carvanha","qt":1},{"name":"glameow","qt":1},{"name":"nihilego","qt":1},{"name":"mantine","qt":1}]}